{
  "metadata": {
    "crawl_time": "2026-04-17T18:13:42.292837",
    "source": "https://chobopark.tistory.com/372",
    "total_questions": 20
  },
  "questions": [
    {
      "number": 1,
      "text": "1. 아래 자바 코드에서 출력되는 값을 작성하시오.",
      "question_html": "<p data-ke-size=\"size16\" style=\"color: #555555; text-align: start;\"><b>1. 아래 자바 코드에서 출력되는 값을 작성하시오.</b></p>",
      "options": "",
      "images": [],
      "code": "class Static{\n    public int a = 20;\n    static int b = 0;\n}\npublic class Main{\n    public static void main(String[] args) {\n        int a;\n        a = 10;\n        Static.b = a;\n        Static st = new Static();\n        System.out.println(Static.b++);\n        System.out.println(st.b);\n        System.out.println(a);\n        System.out.print(st.a);\n    }\n}",
      "code_html": "<div class=\"code-line\"><span style=\"color: #a71d5d;\">class</span> Static{</div>\n<div class=\"code-line\">    <span style=\"color: #a71d5d;\">public</span> <span style=\"color: #066de2;\">int</span> a <span style=\"color: #a71d5d;\">=</span> <span style=\"color: #0099cc;\">20</span>;</div>\n<div class=\"code-line\">    <span style=\"color: #a71d5d;\">static</span> <span style=\"color: #066de2;\">int</span> b <span style=\"color: #a71d5d;\">=</span> <span style=\"color: #0099cc;\">0</span>;</div>\n<div class=\"code-line\">}</div>\n<div class=\"code-line\"><span style=\"color: #a71d5d;\">public</span> <span style=\"color: #a71d5d;\">class</span> Main{</div>\n<div class=\"code-line\">    <span style=\"color: #a71d5d;\">public</span> <span style=\"color: #a71d5d;\">static</span> <span style=\"color: #a71d5d;\">void</span> main(<span style=\"color: #066de2;\">String</span>[] args) {</div>\n<div class=\"code-line\">        <span style=\"color: #066de2;\">int</span> a;</div>\n<div class=\"code-line\">        a <span style=\"color: #a71d5d;\">=</span> <span style=\"color: #0099cc;\">10</span>;</div>\n<div class=\"code-line\">        Static.b <span style=\"color: #a71d5d;\">=</span> a;</div>\n<div class=\"code-line\">        Static st <span style=\"color: #a71d5d;\">=</span> <span style=\"color: #a71d5d;\">new</span> Static();</div>\n<div class=\"code-line\">        <span style=\"color: #066de2;\">System</span>.<span style=\"color: #066de2;\">out</span>.<span style=\"color: #066de2;\">println</span>(Static.b<span style=\"color: #a71d5d;\">+</span><span style=\"color: #a71d5d;\">+</span>);</div>\n<div class=\"code-line\">        <span style=\"color: #066de2;\">System</span>.<span style=\"color: #066de2;\">out</span>.<span style=\"color: #066de2;\">println</span>(st.b);</div>\n<div class=\"code-line\">        <span style=\"color: #066de2;\">System</span>.<span style=\"color: #066de2;\">out</span>.<span style=\"color: #066de2;\">println</span>(a);</div>\n<div class=\"code-line\">        <span style=\"color: #066de2;\">System</span>.<span style=\"color: #066de2;\">out</span>.<span style=\"color: #066de2;\">print</span>(st.a);</div>\n<div class=\"code-line\">    }</div>\n<div class=\"code-line\">}</div>",
      "answer": "10\n11\n10\n20",
      "answer_html": "<p data-ke-size=\"size16\" style=\"color: #555555; text-align: start;\">10</p>\n<p data-ke-size=\"size16\" style=\"color: #555555; text-align: start;\">11</p>\n<p data-ke-size=\"size16\" style=\"color: #555555; text-align: start;\">10</p>\n<p data-ke-size=\"size16\" style=\"color: #555555; text-align: start;\">20</p>"
    },
    {
      "number": 2,
      "text": "2. 다음 C언어의 출력값을 작성하시오.",
      "question_html": "<p data-ke-size=\"size16\" style=\"color: #555555; text-align: start;\"><b>2. 다음 C언어의 출력값을 작성하시오.</b></p>",
      "options": "",
      "images": [],
      "code": "#include <stdio.h>\nint main(){\n    char a[] = \"Art\";\n    char* p = NULL;\n    p = a;\n    printf(\"%s\\n\", a);\n    printf(\"%c\\n\", *p);\n    printf(\"%c\\n\", *a);\n    printf(\"%s\\n\", p);\n    for(int i = 0; a[i] != '\\0'; i++)\n    printf(\"%c\", a[i]);\n}",
      "code_html": "<div class=\"code-line\"><span style=\"color: #0086b3;\">#include</span> <span style=\"color: #a71d5d;\">&lt;</span>stdio.h<span style=\"color: #a71d5d;\">&gt;</span></div>\n<div class=\"code-line\"><span style=\"color: #066de2;\">int</span> main(){</div>\n<div class=\"code-line\">    <span style=\"color: #066de2;\">char</span> a[] <span style=\"color: #a71d5d;\">=</span> <span style=\"color: #63a35c;\">\"Art\"</span>;</div>\n<div class=\"code-line\">    <span style=\"color: #066de2;\">char</span><span style=\"color: #a71d5d;\">*</span> p <span style=\"color: #a71d5d;\">=</span> <span style=\"color: #0086b3;\">NULL</span>;</div>\n<div class=\"code-line\">    p <span style=\"color: #a71d5d;\">=</span> a;</div>\n<div class=\"code-line\">    <span style=\"color: #066de2;\">printf</span>(<span style=\"color: #63a35c;\">\"%s\\n\"</span>, a);</div>\n<div class=\"code-line\">    <span style=\"color: #066de2;\">printf</span>(<span style=\"color: #63a35c;\">\"%c\\n\"</span>, <span style=\"color: #a71d5d;\">*</span>p);</div>\n<div class=\"code-line\">    <span style=\"color: #066de2;\">printf</span>(<span style=\"color: #63a35c;\">\"%c\\n\"</span>, <span style=\"color: #a71d5d;\">*</span>a);</div>\n<div class=\"code-line\">    <span style=\"color: #066de2;\">printf</span>(<span style=\"color: #63a35c;\">\"%s\\n\"</span>, p);</div>\n<div class=\"code-line\">    <span style=\"color: #a71d5d;\">for</span>(<span style=\"color: #066de2;\">int</span> i <span style=\"color: #a71d5d;\">=</span> <span style=\"color: #0099cc;\">0</span>; a[i] <span style=\"color: #a71d5d;\">!</span><span style=\"color: #a71d5d;\">=</span> <span style=\"color: #63a35c;\">'\\0'</span>; i<span style=\"color: #a71d5d;\">+</span><span style=\"color: #a71d5d;\">+</span>)</div>\n<div class=\"code-line\">    <span style=\"color: #066de2;\">printf</span>(<span style=\"color: #63a35c;\">\"%c\"</span>, a[i]);</div>\n<div class=\"code-line\">}</div>",
      "answer": "Art\nA\nA\nArt\nArt",
      "answer_html": "<p data-ke-size=\"size16\" style=\"color: #555555; text-align: start;\">Art</p>\n<p data-ke-size=\"size16\" style=\"color: #555555; text-align: start;\">A</p>\n<p data-ke-size=\"size16\" style=\"color: #555555; text-align: start;\">A</p>\n<p data-ke-size=\"size16\" style=\"color: #555555; text-align: start;\">Art</p>\n<p data-ke-size=\"size16\" style=\"color: #555555; text-align: start;\">Art</p>"
    },
    {
      "number": 3,
      "text": "3. 다음 C언어의 출력값을 작성하시오.",
      "question_html": "<p data-ke-size=\"size16\" style=\"color: #555555; text-align: start;\"><b>3. 다음 C언어의 출력값을 작성하시오.</b></p>",
      "options": "",
      "images": [],
      "code": "#include <stdio.h>\nint main(){\n    char* a = \"qwer\";\n    char* b = \"qwtety\";\n    for(int i = 0; a[i] != '\\0' ; i++){\n        for(int j = 0; b[j] != '\\0'; j++){\n            if(a[i] == b[j]) printf(\"%c\", a[i]);\n        }\n    }\n}",
      "code_html": "<div class=\"code-line\"><span style=\"color: #0086b3;\">#include</span> <span style=\"color: #a71d5d;\">&lt;</span>stdio.h<span style=\"color: #a71d5d;\">&gt;</span></div>\n<div class=\"code-line\"><span style=\"color: #066de2;\">int</span> main(){</div>\n<div class=\"code-line\">    <span style=\"color: #066de2;\">char</span><span style=\"color: #a71d5d;\">*</span> a <span style=\"color: #a71d5d;\">=</span> <span style=\"color: #63a35c;\">\"qwer\"</span>;</div>\n<div class=\"code-line\">    <span style=\"color: #066de2;\">char</span><span style=\"color: #a71d5d;\">*</span> b <span style=\"color: #a71d5d;\">=</span> <span style=\"color: #63a35c;\">\"qwtety\"</span>;</div>\n<div class=\"code-line\">    <span style=\"color: #a71d5d;\">for</span>(<span style=\"color: #066de2;\">int</span> i <span style=\"color: #a71d5d;\">=</span> <span style=\"color: #0099cc;\">0</span>; a[i] <span style=\"color: #a71d5d;\">!</span><span style=\"color: #a71d5d;\">=</span> <span style=\"color: #63a35c;\">'\\0'</span> ; i<span style=\"color: #a71d5d;\">+</span><span style=\"color: #a71d5d;\">+</span>){</div>\n<div class=\"code-line\">        <span style=\"color: #a71d5d;\">for</span>(<span style=\"color: #066de2;\">int</span> j <span style=\"color: #a71d5d;\">=</span> <span style=\"color: #0099cc;\">0</span>; b[j] <span style=\"color: #a71d5d;\">!</span><span style=\"color: #a71d5d;\">=</span> <span style=\"color: #63a35c;\">'\\0'</span>; j<span style=\"color: #a71d5d;\">+</span><span style=\"color: #a71d5d;\">+</span>){</div>\n<div class=\"code-line\">            <span style=\"color: #a71d5d;\">if</span>(a[i] <span style=\"color: #a71d5d;\">=</span><span style=\"color: #a71d5d;\">=</span> b[j]) <span style=\"color: #066de2;\">printf</span>(<span style=\"color: #63a35c;\">\"%c\"</span>, a[i]);</div>\n<div class=\"code-line\">        }</div>\n<div class=\"code-line\">    }</div>\n<div class=\"code-line\">}</div>",
      "answer": "qwe",
      "answer_html": "<p data-ke-size=\"size16\" style=\"color: #555555; text-align: start;\">qwe</p>"
    },
    {
      "number": 4,
      "text": "4. 다음 괄호안에 들어가는 용어의 Full Name 또는 약자를 작성하시오.\n( )은/는 비동기적인 웹 애플리케이션의 제작을 위해 JavaScript와 XML을 이용한 비동기적 정보 교환 기법이다. ( )은/는 필요한 데이터만을 웹서버에 요청해서 받은 후 클라이언트에서 데이터에 대한 처리를 할 수 있다. 보통 SOAP이나 XML 기반의 웹 서비스 프로토콜이 사용되며, 웹 서버의 응답을 처리하기 위해 클라이언트 쪽에서는 자바스크립트를 쓴다. ( )은/는 Google Map과 Google pages에서 사용한 기술에 기반하여 제작되었다.",
      "question_html": "<p data-ke-size=\"size16\" style=\"color: #555555; text-align: start;\"><b>4. 다음 괄호안에 들어가는 용어의 Full Name 또는 약자를 작성하시오.</b></p>\n<p data-ke-size=\"size16\" style=\"color: #555555; text-align: start;\">(   )은/는 비동기적인 웹 애플리케이션의 제작을 위해 JavaScript와 XML을 이용한 비동기적 정보 교환 기법이다. (   )은/는 필요한 데이터만을 웹서버에 요청해서 받은 후 클라이언트에서 데이터에 대한 처리를 할 수 있다.  보통 SOAP이나 XML 기반의 웹 서비스 프로토콜이 사용되며, 웹 서버의 응답을 처리하기 위해 클라이언트 쪽에서는 자바스크립트를 쓴다. (   )은/는 Google Map과 Google pages에서 사용한 기술에 기반하여 제작되었다.</p>",
      "options": "",
      "images": [],
      "code": null,
      "code_html": null,
      "answer": "AJAX (Asynchronous JavaScript and XML)",
      "answer_html": "<p data-ke-size=\"size16\" style=\"color: #555555; text-align: start;\">AJAX (Asynchronous JavaScript and XML)</p>"
    },
    {
      "number": 5,
      "text": "5.\n아래 내용을 확인하여 괄호 안에 용어를 표안에 알맞는 값을 고르시오.\n(보기가 있습니다.\nex: 패킷​\n등)\n구분\n내용\n( )\n- 회선교환 방식과 데이터그램 방식의 장점을 결합한 통신 기술이다. - 처음 패킷으로 최적의 경로를 고정하고 경로가 고정되면 그 다음은 패킷으로 나누어 고속으로 전송할 수 있다. - 통신기술에는 ATM이 있으며, 정해진 시간 안이나 다량의 데이터를 연속으로 보낼 때 적합하다.\n( )\n- 패킷교환 방식으로 동작하면서 IP 주소를 사용하는 인터넷을 의미한다. - 각 전송패킷을 미리 정해진 경로 없이 독립적으로 처리하여 교환하는 방식이다 - 특정 교환기의 고장 시 모든 패킷을 잃어버리는 가상회선과 달리, 그 경로를 피해서 전송할 수 있으므로 더욱 신뢰가 가능하다. - 짧은 메시지의 패킷들을 전송할 때 효과적이고 재정렬 기능이 필요하다.",
      "question_html": "<p data-ke-size=\"size16\" style=\"color: #555555; text-align: start;\"><b>5. <b>아래 내용을 확인하여 괄호 안에 용어를 표안에 알맞는 값을 고르시오.</b></b></p>\n<p data-ke-size=\"size16\" style=\"color: #555555; text-align: start;\"><u>(보기가 있습니다.<u>ex: 패킷​ </u>등)</u></p>\n<table border=\"1\" data-ke-align=\"alignLeft\" style=\"border-collapse: collapse; width: 100%; height: 54px;\">\n<tbody>\n<tr style=\"height: 20px;\">\n<td style=\"width: 32.2093%; text-align: center; height: 20px;\">구분</td>\n<td style=\"width: 67.7907%; text-align: center; height: 20px;\">내용</td>\n</tr>\n<tr style=\"height: 17px;\">\n<td style=\"width: 32.2093%; text-align: center; height: 17px;\">(   )</td>\n<td style=\"width: 67.7907%; height: 17px; text-align: left;\"> - 회선교환 방식과 데이터그램 방식의 장점을 결합한 통신 기술이다. - 처음 패킷으로 최적의 경로를 고정하고 경로가 고정되면 그 다음은 패킷으로 나누어 고속으로 전송할 수 있다. - 통신기술에는 ATM이 있으며, 정해진 시간 안이나 다량의 데이터를 연속으로 보낼 때 적합하다.</td>\n</tr>\n<tr style=\"height: 17px;\">\n<td style=\"width: 32.2093%; text-align: center; height: 17px;\">(   )</td>\n<td style=\"width: 67.7907%; height: 17px; text-align: left;\"> - 패킷교환 방식으로 동작하면서 IP 주소를 사용하는 인터넷을 의미한다.  - 각 전송패킷을 미리 정해진 경로 없이 독립적으로 처리하여 교환하는 방식이다  - 특정 교환기의 고장 시 모든 패킷을 잃어버리는 가상회선과 달리, 그 경로를 피해서 전송할 수 있으므로 더욱 신뢰가 가능하다.  - 짧은 메시지의 패킷들을 전송할 때 효과적이고 재정렬 기능이 필요하다.</td>\n</tr>\n</tbody>\n</table>",
      "options": "",
      "images": [],
      "code": null,
      "code_html": null,
      "answer": "가상회선, 데이터그램",
      "answer_html": "<p data-ke-size=\"size16\" style=\"color: #555555; text-align: start;\">가상회선, 데이터그램</p>"
    },
    {
      "number": 6,
      "text": "6. 아래 내용을 확인하여 알맞는 답을 작성하시오.\n2 계층(데이터링크 계층)에서 구현되는 터널링 기술 중 하나\nL2F와 PPTP가 결합된 프로토콜로 VPN과 인터넷 서비스 제공자(ISP)가 이용\nIPsec을 함께 사용하면 PPTP보다 훨씬 안전하지만 보안보다 익명화에 더 적합",
      "question_html": "<p data-ke-size=\"size16\" style=\"color: #555555; text-align: start;\"><b>6. 아래 내용을 확인하여 알맞는 답을 작성하시오.</b></p>\n<ul data-ke-list-type=\"disc\" style=\"list-style-type: disc;\">\n<li>2 계층(데이터링크 계층)에서 구현되는 터널링 기술 중 하나</li>\n<li>L2F와 PPTP가 결합된 프로토콜로 VPN과 인터넷 서비스 제공자(ISP)가 이용</li>\n<li>IPsec을 함께 사용하면 PPTP보다 훨씬 안전하지만 보안보다 익명화에 더 적합</li>\n</ul>",
      "options": "",
      "images": [],
      "code": null,
      "code_html": null,
      "answer": "L2TP",
      "answer_html": "<p data-ke-size=\"size16\" style=\"color: #555555; text-align: start;\">L2TP</p>"
    },
    {
      "number": 7,
      "text": "7.\n아래 내용에서 괄호안에 알맞는 용어를 작성하시오.\n​\n( ) 네트워크 상의 다른 컴퓨터에 로그인하거나 원격 시스템에서 명령을 실행하고 다른 시스템으로 파일을 복사할 수 있도록 해주는 응용 프로그램 또는 그 프로토콜을 가리킨다.\n( ) 보안 접속을 통한 rsh, rcp, rlogin, rexec, telnet, ftp 등을 제공하며, IP spoofing (IP스푸핑, 아이피 위/변조 기법중 하나)을 방지하기 위한 기능을 제공한다.\n( ) 기본적으로 포트는 22번이다.​",
      "question_html": "<p data-ke-size=\"size16\" style=\"color: #555555; text-align: start;\"><b>7. <b>아래 내용에서 괄호안에 알맞는 용어를 작성하시오.</b></b>​</p>\n<p data-ke-size=\"size16\" style=\"color: #555555; text-align: start;\">(    )  네트워크 상의 다른 컴퓨터에 로그인하거나 원격 시스템에서 명령을 실행하고 다른 시스템으로 파일을 복사할 수 있도록 해주는 응용 프로그램 또는 그 프로토콜을 가리킨다.</p>\n<p data-ke-size=\"size16\" style=\"color: #555555; text-align: start;\">(    )  보안 접속을 통한 rsh, rcp, rlogin, rexec, telnet, ftp 등을 제공하며, IP spoofing (IP스푸핑, 아이피 위/변조 기법중 하나)을 방지하기 위한 기능을 제공한다.</p>\n<p data-ke-size=\"size16\" style=\"color: #555555; text-align: start;\">(    )  기본적으로 포트는 22번이다.​</p>",
      "options": "",
      "images": [],
      "code": null,
      "code_html": null,
      "answer": "SSH (Secure SHell)",
      "answer_html": "<p data-ke-size=\"size16\" style=\"color: #555555; text-align: start;\">SSH (Secure SHell)</p>"
    },
    {
      "number": 8,
      "text": "8. 아래 설명에 대한 알맞는 답을 작성하시오.\n(보기가 있습니다.\nex:\n랜섬웨어,\n스파이웨어\n​\n등)\n구분\n내용\n( 1 )\n- 감염된 컴퓨터 시스템에서 스스로 복제해 다른 컴퓨터로 복사본을 확산시킬 수 있는 악성 프로그램이다. - 독자적으로 실행되며 다른 실행 프로그램이 필요하지 않으며, 파일 전송 기능을 착취하도록 설계된다. - 자가 복제 및 네트워크를 통한 전파도 가능하다.\n( 2 )\n- 정상적인 프로그램으로 가장해 사용자가 직접 컴퓨터에 설치하도록 위장하며, 백도어를 만들어 공격자가 침입할 수 있도록 만들거나 시스템을 파괴한다. - 정상적인 프로그램으로 위장하여 시작부터 끝까지 램에 상주하며, 시스템 내부 정보를 공격자의 컴퓨터로 빼돌리는 프로그램이다. - 좀비PC처럼 내부정보 유출뿐만 아니라 컨트롤까지 가능한 종류가 있고, 단순히 내부 데이터만 유출할 수 있는 타입의 트로이 목마가 있다. - 감염된 후에 스스로를 복제하는 능력은 없다.\n( 3 )\n- 대상(정상파일)을 감염시키는 형태로 실행되며, 감염시킬 대상이 존재하지 않을 때에는 실행되지 않으며 다른정상파일로의 자기 복제 기능이 있다. - 컴퓨터 시스템에 침입해 프로그램에 기생하며 시스템을 변경하거나 사용할 수 없도록 만드는 악성코드이다. - 네트워크를 통해 전파되지 않으며 방식 및 위치에 따라 여러형태로 나뉜다.",
      "question_html": "<p data-ke-size=\"size16\" style=\"color: #555555; text-align: start;\"><b>8. 아래 설명에 대한 알맞는 답을 작성하시오.</b></p>\n<p data-ke-size=\"size16\" style=\"color: #555555; text-align: start;\"><u>(보기가 있습니다.<u>ex: <span style=\"background-color: #ffffff; color: #202124; text-align: left;\">랜섬웨어, <span style=\"background-color: #ffffff; color: #202124; text-align: left;\">스파이웨어</span></span>​</u>등)</u></p>\n<table border=\"1\" data-ke-align=\"alignLeft\" style=\"border-collapse: collapse; width: 100%; height: 71px;\">\n<tbody>\n<tr style=\"height: 20px;\">\n<td style=\"width: 31.2791%; text-align: center; height: 20px;\">구분</td>\n<td style=\"width: 68.7209%; text-align: center; height: 20px;\">내용</td>\n</tr>\n<tr style=\"height: 17px;\">\n<td style=\"width: 31.2791%; text-align: center; height: 17px;\">(   1   )</td>\n<td style=\"width: 68.7209%; height: 17px; text-align: left;\">- 감염된 컴퓨터 시스템에서 스스로 복제해 다른 컴퓨터로 복사본을 확산시킬 수 있는 악성 프로그램이다. - 독자적으로 실행되며 다른 실행 프로그램이 필요하지 않으며, 파일 전송 기능을 착취하도록 설계된다. - 자가 복제 및 네트워크를 통한 전파도 가능하다.</td>\n</tr>\n<tr style=\"height: 17px;\">\n<td style=\"width: 31.2791%; text-align: center; height: 17px;\">(    2    )</td>\n<td style=\"width: 68.7209%; height: 17px; text-align: left;\">- 정상적인 프로그램으로 가장해 사용자가 직접 컴퓨터에 설치하도록 위장하며, 백도어를 만들어 공격자가 침입할 수 있도록 만들거나 시스템을 파괴한다. - 정상적인 프로그램으로 위장하여 시작부터 끝까지 램에 상주하며, 시스템 내부 정보를 공격자의 컴퓨터로 빼돌리는 프로그램이다.  - 좀비PC처럼 내부정보 유출뿐만 아니라 컨트롤까지 가능한 종류가 있고, 단순히 내부 데이터만 유출할 수 있는 타입의 트로이 목마가 있다. - 감염된 후에 스스로를 복제하는 능력은 없다.</td>\n</tr>\n<tr style=\"height: 17px;\">\n<td style=\"width: 31.2791%; text-align: center; height: 17px;\">(    3    )</td>\n<td style=\"width: 68.7209%; height: 17px; text-align: left;\">- 대상(정상파일)을 감염시키는 형태로 실행되며, 감염시킬 대상이 존재하지 않을 때에는 실행되지 않으며 다른정상파일로의 자기 복제 기능이 있다. - 컴퓨터 시스템에 침입해 프로그램에 기생하며 시스템을 변경하거나 사용할 수 없도록 만드는 악성코드이다. - 네트워크를 통해 전파되지 않으며 방식 및 위치에 따라 여러형태로 나뉜다.</td>\n</tr>\n</tbody>\n</table>",
      "options": "",
      "images": [],
      "code": null,
      "code_html": null,
      "answer": "1. 웜\n2. 트로이 목마\n3. 바이러스",
      "answer_html": "<p data-ke-size=\"size16\" style=\"color: #555555; text-align: start;\">1. 웜</p>\n<p data-ke-size=\"size16\" style=\"color: #555555; text-align: start;\">2. 트로이 목마</p>\n<p data-ke-size=\"size16\" style=\"color: #555555; text-align: start;\">3. 바이러스</p>"
    },
    {
      "number": 9,
      "text": "9. 다음 아래 코드에서 이진수를 십진수로 변환하는 코드에 대해 괄호 (a) (b)의 적합한 답을 작성하시오.",
      "question_html": "<p data-ke-size=\"size16\" style=\"color: #555555; text-align: start;\"><b>9. 다음 아래 코드에서 이진수를 십진수로 변환하는 코드에 대해 괄호 (a) (b)의 적합한 답을 작성하시오.</b></p>",
      "options": "",
      "images": [],
      "code": "#include <stdio.h>\nint main() {\n    int input = 101110;\n    int di = 1;\n    int sum = 0;\n    while (1) {\n        if (input == 0) break\n        else {\n          sum = sum + (input (a)(b)) * di;\n             di = di * 2;\n             input = input / 10;\n        }\n    }\n    printf(\"%d\", sum);\n    return 0;\n}",
      "code_html": "<div class=\"code-line\"><span style=\"color: #0086b3;\">#include</span> <span style=\"color: #a71d5d;\">&lt;</span>stdio.h<span style=\"color: #a71d5d;\">&gt;</span></div>\n<div class=\"code-line\"><span style=\"color: #066de2;\">int</span> main() {</div>\n<div class=\"code-line\">    <span style=\"color: #066de2;\">int</span> input <span style=\"color: #a71d5d;\">=</span> <span style=\"color: #0099cc;\">101110</span>;</div>\n<div class=\"code-line\">    <span style=\"color: #066de2;\">int</span> di <span style=\"color: #a71d5d;\">=</span> <span style=\"color: #0099cc;\">1</span>;</div>\n<div class=\"code-line\">    <span style=\"color: #066de2;\">int</span> sum <span style=\"color: #a71d5d;\">=</span> <span style=\"color: #0099cc;\">0</span>;</div>\n<div class=\"code-line\">    <span style=\"color: #a71d5d;\">while</span> (<span style=\"color: #0099cc;\">1</span>) {</div>\n<div class=\"code-line\">        <span style=\"color: #a71d5d;\">if</span> (input <span style=\"color: #a71d5d;\">=</span><span style=\"color: #a71d5d;\">=</span> <span style=\"color: #0099cc;\">0</span>) <span style=\"color: #a71d5d;\">break</span></div>\n<div class=\"code-line\">        <span style=\"color: #a71d5d;\">else</span> {</div>\n<div class=\"code-line\">          sum <span style=\"color: #a71d5d;\">=</span> sum <span style=\"color: #a71d5d;\">+</span> (input (a)(b)) <span style=\"color: #a71d5d;\">*</span> di;</div>\n<div class=\"code-line\">             di <span style=\"color: #a71d5d;\">=</span> di <span style=\"color: #a71d5d;\">*</span> <span style=\"color: #0099cc;\">2</span>;</div>\n<div class=\"code-line\">             input <span style=\"color: #a71d5d;\">=</span> input <span style=\"color: #a71d5d;\">/</span> <span style=\"color: #0099cc;\">10</span>;</div>\n<div class=\"code-line\">        }</div>\n<div class=\"code-line\">    }</div>\n<div class=\"code-line\">    <span style=\"color: #066de2;\">printf</span>(<span style=\"color: #63a35c;\">\"%d\"</span>, sum);</div>\n<div class=\"code-line\">    <span style=\"color: #a71d5d;\">return</span> <span style=\"color: #0099cc;\">0</span>;</div>\n<div class=\"code-line\">}</div>",
      "answer": "1. (a) % ,(b) 10 or 5 or 2 2. (a) & ,(b) 1",
      "answer_html": "<p data-ke-size=\"size16\" style=\"color: #555555; text-align: start;\">1. (a) %  ,(b) 10 or 5 or 2 2. (a) &amp;  ,(b) 1</p>"
    },
    {
      "number": 10,
      "text": "10. 다음 보안 관련 설명으로 괄호안에 알맞는 용어를 작성하시오.\n( )은/는 TCP/IP에서 IP 패킷을 처리할 때 발생되는 문제를 알려주는 프로토콜이다.\n( ) 프로토콜은 보통 다른 호스트나 게이트웨이 와 연결된 네트웍에 문제가 있는지 확인하기 위한 목적으로 주로 사용된다.\n( ) 을/를 이용한 공격에는\n( )\nFlooding가 있는데 ping 명령어를 통한 ( ) 패킷을 연속적으로 계속 보내어 서버의 요청에 응답으로 인한 다른작업을 하지 못하도록 하는 공격이다.\n반응형",
      "question_html": "<p data-ke-size=\"size16\" style=\"color: #555555; text-align: start;\"><b>10. 다음 보안 관련 설명으로 괄호안에 알맞는 용어를  작성하시오.</b></p>\n<p data-ke-size=\"size16\" style=\"color: #555555; text-align: start;\">(    )은/는 TCP/IP에서 IP 패킷을 처리할 때 발생되는 문제를 알려주는 프로토콜이다.</p>\n<p data-ke-size=\"size16\" style=\"color: #555555; text-align: start;\">(    ) 프로토콜은 보통 다른 호스트나 게이트웨이 와 연결된 네트웍에 문제가 있는지 확인하기 위한 목적으로 주로 사용된다.</p>\n<p data-ke-size=\"size16\" style=\"color: #555555; text-align: start;\">(    ) 을/를 이용한 공격에는 <span style=\"color: #555555; text-align: start;\">(    )</span> Flooding가 있는데 ping 명령어를 통한 (     ) 패킷을 연속적으로 계속 보내어 서버의 요청에 응답으로 인한 다른작업을 하지 못하도록 하는 공격이다. </p>\n<div class=\"revenue_unit_wrap\">\n<div class=\"revenue_unit_item adsense responsive\">\n<div class=\"revenue_unit_info\">반응형</div>\n<script>(adsbygoogle = window.adsbygoogle || []).push({});</script>\n</div>\n</div>",
      "options": "",
      "images": [],
      "code": null,
      "code_html": null,
      "answer": "ICMP",
      "answer_html": "<p data-ke-size=\"size16\" style=\"color: #555555; text-align: start;\">ICMP</p>"
    },
    {
      "number": 11,
      "text": "11. 다음은 디자인 패턴에 관한 설명이다. 설명에 내용에 알맞는 답을 고르시오.\n(생성/구조/행위 별로 표형태의 보기가 있습니다.\nex:\nBuilder, Bridge\n​\n등)\n- 다른 무언가와 이어지는 인터페이스 역할을 하는 클래스를 의미한다.\n- 실제 객체를 호출하면 행위를 중간에 가로채서 다른 동작을 수행하는 객체로 변경한다.\n- 객체를 정교하게 제어해야 하거나 객체 참조가 필요한 경우 사용한다.\n- 분리된 객체를 위임함으로써 대리 작업을 중간 단계에 삽입할 수도 있으며 분리된 객체를 동적으로 연결함으로써 객체의 실행 시점을 관리할 수도 있다.",
      "question_html": "<p data-ke-size=\"size16\" style=\"color: #555555; text-align: start;\"><b>11. 다음은 디자인 패턴에 관한 설명이다. 설명에 내용에 알맞는 답을 고르시오.</b></p>\n<p data-ke-size=\"size16\" style=\"color: #555555; text-align: start;\"><u>(생성/구조/행위 별로 표형태의 보기가 있습니다.<u>ex:<span> Builder, Bridge</span>​</u>등)</u></p>\n<p data-ke-size=\"size16\" style=\"color: #555555; text-align: start;\">- 다른 무언가와 이어지는 인터페이스 역할을 하는 클래스를 의미한다.</p>\n<p data-ke-size=\"size16\" style=\"color: #555555; text-align: start;\">- 실제 객체를 호출하면 행위를 중간에 가로채서 다른 동작을 수행하는 객체로 변경한다.</p>\n<p data-ke-size=\"size16\" style=\"color: #555555; text-align: start;\">- 객체를 정교하게 제어해야 하거나 객체 참조가 필요한 경우 사용한다.</p>\n<p data-ke-size=\"size16\" style=\"color: #555555; text-align: start;\">- 분리된 객체를 위임함으로써 대리 작업을 중간 단계에 삽입할 수도 있으며 분리된 객체를 동적으로 연결함으로써 객체의 실행 시점을 관리할 수도 있다.</p>",
      "options": "",
      "images": [],
      "code": null,
      "code_html": null,
      "answer": "proxy",
      "answer_html": "<p data-ke-size=\"size16\" style=\"color: #555555; text-align: start;\">proxy</p>"
    },
    {
      "number": 12,
      "text": "12.\n다음은 데이터베이스에 관련된 내용이다. 각 괄호안에 알맞는 답을 작성하시오.\n(보기가 있습니다.\nex:\n릴레이션 스키마\n​\n등)\n구분\n내용\n( 1 )\n- 셀 수 있는 수량의 순서 있는 열거이다. - 어떤 요소의 집합, 혹은 테이블에서의 행을 가리키지만 일반적인 집합과는 달리 중복이 허용될 수 있다. - 리스트와 동일하게 여러 객체를 모아서 담으며, 숫자, 문자, 객체, 배열, 튜플 안의 튜플 전부 가능하다.\n( 2 )\n- 어느 한 시점에 릴레이션의 내용(상태), 즉 저장된 데이터 전체를 의미한다. - 단순히 릴레이션 또는 릴레이션 외연(Relation Extension)라고도 한다.\n( 3 )\n- 특정 데이터 집합의 유니크(Unique)한 값의 개수이다. - 전체 행에 대한 특정 컬럼의 중복 수치를 나타내는 지표이다.",
      "question_html": "<p data-ke-size=\"size16\" style=\"color: #555555; text-align: start;\"><b>12.<span> 다음은 데이터베이스에 관련된 내용이다. 각 괄호안에 알맞는 답을 작성하시오.</span></b></p>\n<p data-ke-size=\"size16\" style=\"color: #555555; text-align: start;\"><u>(보기가 있습니다.<u>ex:<span><span> 릴레이션 스키마</span></span>​</u>등)</u></p>\n<table border=\"1\" data-ke-align=\"alignLeft\" style=\"border-collapse: collapse; width: 100%;\">\n<tbody>\n<tr>\n<td style=\"width: 26.3953%; text-align: center;\">구분</td>\n<td style=\"width: 73.6047%; text-align: center;\">내용</td>\n</tr>\n<tr>\n<td style=\"width: 26.3953%; text-align: center;\">(   1   )</td>\n<td style=\"width: 73.6047%; text-align: left;\">- 셀 수 있는 수량의 순서 있는 열거이다. - 어떤 요소의 집합, 혹은 테이블에서의 행을 가리키지만 일반적인 집합과는 달리 중복이 허용될 수 있다. - 리스트와 동일하게 여러 객체를 모아서 담으며, 숫자, 문자, 객체, 배열, 튜플 안의 튜플 전부 가능하다.</td>\n</tr>\n<tr>\n<td style=\"width: 26.3953%; text-align: center;\">(   2   )</td>\n<td style=\"width: 73.6047%; text-align: left;\">- 어느 한 시점에 릴레이션의 내용(상태), 즉 저장된 데이터 전체를 의미한다. - 단순히 릴레이션 또는 릴레이션 외연(Relation Extension)라고도 한다.</td>\n</tr>\n<tr>\n<td style=\"width: 26.3953%; text-align: center;\">(   3   )</td>\n<td style=\"width: 73.6047%; text-align: left;\">- 특정 데이터 집합의 유니크(Unique)한 값의 개수이다. - 전체 행에 대한 특정 컬럼의 중복 수치를 나타내는 지표이다.</td>\n</tr>\n</tbody>\n</table>",
      "options": "",
      "images": [],
      "code": null,
      "code_html": null,
      "answer": "1. 튜플\n2. 릴레이션 인스턴스\n3. 카디널리티",
      "answer_html": "<p data-ke-size=\"size16\" style=\"color: #555555; text-align: start;\">1. 튜플</p>\n<p data-ke-size=\"size16\" style=\"color: #555555; text-align: start;\">2. 릴레이션 인스턴스</p>\n<p data-ke-size=\"size16\" style=\"color: #555555; text-align: start;\">3. 카디널리티</p>"
    },
    {
      "number": 13,
      "text": "13.\n[학생] 테이블에서 학생 이름이 '민수'인 튜플을 삭제하는 쿼리를 작성하시오.\n조건\n- 컬럼의 값이 문자열일 경우 작은 따움표 (' ')를 표시하시오. - SQL 마지막에 세미콜론(;)은 표기하지 않아도 관계 없습니다.",
      "question_html": "<p data-ke-size=\"size16\" style=\"color: #555555; text-align: start;\"><b>13.<span><span> [학생] 테이블에서 학생 이름이 '민수'인 튜플을 삭제하는 쿼리를 작성하시오.</span></span></b></p>\n<p data-ke-size=\"size16\" style=\"color: #555555; text-align: start;\"><b>조건</b> - 컬럼의 값이 문자열일 경우 작은 따움표 ('  ')를 표시하시오. - SQL 마지막에 세미콜론(;)은 표기하지 않아도 관계 없습니다.</p>",
      "options": "",
      "images": [],
      "code": null,
      "code_html": null,
      "answer": "delete from 학생 where 이름 = '민수';",
      "answer_html": "<p data-ke-size=\"size16\" style=\"color: #555555; text-align: start;\"><b><span><span>delete from 학생 where 이름 = '민수';</span></span></b></p>"
    },
    {
      "number": 14,
      "text": "14.\n다음 코드에서 괄호안에 알맞는 값을 변수명으로 작성하시오.\n(코드가 해깔려 시험문제와 동일하지 않지만 패턴이 비슷하다는 점만 참고해주세요.)\n출력 값 : 1 2 3 5 7 8",
      "question_html": "<p data-ke-size=\"size16\" style=\"color: #555555; text-align: start;\"><b>14.<span><span><span> 다음 코드에서 괄호안에 알맞는 값을 변수명으로 작성하시오.</span></span></span></b></p>\n<p data-ke-size=\"size16\" style=\"color: #555555; text-align: start;\"><u>(코드가 해깔려 시험문제와 동일하지 않지만 패턴이 비슷하다는 점만 참고해주세요.)</u></p>\n<p data-ke-size=\"size16\" style=\"color: #555555; text-align: start;\"><b>출력 값 : 1 2 3 5 7 8</b></p>",
      "options": "",
      "images": [],
      "code": "public class Sort {\n    public static void swap(int[] arr, int idx1, int idx2){\n        int temp = arr[idx1];\n        arr[idx1] = arr[idx2];\n        arr[( 1 )] = temp;\n    }\n    public static void Usort(int[] array, int length){\n        for (int i = 0; i < length; i++) {\n            for (int j = 0; j < length - i - 1; j++) {\n                if (array[j] > array[j + 1]) {\n                    swap(array, j, j + 1);\n                }\n            }\n        }\n    }\n    public static void main(String[] args) {\n        int[] item = new int[] { 5, 3, 8, 1, 2, 7 };\n        int nx = 6;\n        Usort(item, ( 2 ));\n        for (int data : item) {\n            System.out.print(data + \" \");\n        }\n    }\n}",
      "code_html": "<div class=\"code-line\"><span style=\"color: #a71d5d;\">public</span> <span style=\"color: #a71d5d;\">class</span> Sort {</div>\n<div class=\"code-line\">    <span style=\"color: #a71d5d;\">public</span> <span style=\"color: #a71d5d;\">static</span> <span style=\"color: #a71d5d;\">void</span> swap(<span style=\"color: #066de2;\">int</span>[] arr, <span style=\"color: #066de2;\">int</span> idx1, <span style=\"color: #066de2;\">int</span> idx2){</div>\n<div class=\"code-line\">        <span style=\"color: #066de2;\">int</span> temp <span style=\"color: #a71d5d;\">=</span> arr[idx1];</div>\n<div class=\"code-line\">        arr[idx1] <span style=\"color: #a71d5d;\">=</span> arr[idx2];</div>\n<div class=\"code-line\">        arr[( <span style=\"color: #0099cc;\">1</span> )] <span style=\"color: #a71d5d;\">=</span> temp;</div>\n<div class=\"code-line\">    }</div>\n<div class=\"code-line\">    <span style=\"color: #a71d5d;\">public</span> <span style=\"color: #a71d5d;\">static</span> <span style=\"color: #a71d5d;\">void</span> Usort(<span style=\"color: #066de2;\">int</span>[] array, <span style=\"color: #066de2;\">int</span> <span style=\"color: #066de2;\">length</span>){</div>\n<div class=\"code-line\">        <span style=\"color: #a71d5d;\">for</span> (<span style=\"color: #066de2;\">int</span> i <span style=\"color: #a71d5d;\">=</span> <span style=\"color: #0099cc;\">0</span>; i <span style=\"color: #a71d5d;\">&lt;</span> <span style=\"color: #066de2;\">length</span>; i<span style=\"color: #a71d5d;\">+</span><span style=\"color: #a71d5d;\">+</span>) {</div>\n<div class=\"code-line\">            <span style=\"color: #a71d5d;\">for</span> (<span style=\"color: #066de2;\">int</span> j <span style=\"color: #a71d5d;\">=</span> <span style=\"color: #0099cc;\">0</span>; j <span style=\"color: #a71d5d;\">&lt;</span> <span style=\"color: #066de2;\">length</span> <span style=\"color: #a71d5d;\">-</span> i <span style=\"color: #a71d5d;\">-</span> <span style=\"color: #0099cc;\">1</span>; j<span style=\"color: #a71d5d;\">+</span><span style=\"color: #a71d5d;\">+</span>) {</div>\n<div class=\"code-line\">                <span style=\"color: #a71d5d;\">if</span> (array[j] <span style=\"color: #a71d5d;\">&gt;</span> array[j <span style=\"color: #a71d5d;\">+</span> <span style=\"color: #0099cc;\">1</span>]) {</div>\n<div class=\"code-line\">                    swap(array, j, j <span style=\"color: #a71d5d;\">+</span> <span style=\"color: #0099cc;\">1</span>);</div>\n<div class=\"code-line\">                }</div>\n<div class=\"code-line\">            }</div>\n<div class=\"code-line\">        }</div>\n<div class=\"code-line\">    }</div>\n<div class=\"code-line\">    <span style=\"color: #a71d5d;\">public</span> <span style=\"color: #a71d5d;\">static</span> <span style=\"color: #a71d5d;\">void</span> main(<span style=\"color: #066de2;\">String</span>[] args) {</div>\n<div class=\"code-line\">        <span style=\"color: #066de2;\">int</span>[] item <span style=\"color: #a71d5d;\">=</span> <span style=\"color: #a71d5d;\">new</span> <span style=\"color: #066de2;\">int</span>[] { <span style=\"color: #0099cc;\">5</span>, <span style=\"color: #0099cc;\">3</span>, <span style=\"color: #0099cc;\">8</span>, <span style=\"color: #0099cc;\">1</span>, <span style=\"color: #0099cc;\">2</span>, <span style=\"color: #0099cc;\">7</span> };</div>\n<div class=\"code-line\">        <span style=\"color: #066de2;\">int</span> nx <span style=\"color: #a71d5d;\">=</span> 6;   </div>\n<div class=\"code-line\">        Usort(item, ( <span style=\"color: #0099cc;\">2</span> ));</div>\n<div class=\"code-line\">        <span style=\"color: #a71d5d;\">for</span> (<span style=\"color: #066de2;\">int</span> data : item) {</div>\n<div class=\"code-line\">            <span style=\"color: #066de2;\">System</span>.<span style=\"color: #066de2;\">out</span>.<span style=\"color: #066de2;\">print</span>(data <span style=\"color: #a71d5d;\">+</span> <span style=\"color: #63a35c;\">\" \"</span>);</div>\n<div class=\"code-line\">        }</div>\n<div class=\"code-line\">    }</div>\n<div class=\"code-line\">}</div>",
      "answer": "idx2, nx",
      "answer_html": "<p data-ke-size=\"size16\" style=\"color: #555555; text-align: start;\">idx2, nx</p>"
    },
    {
      "number": 15,
      "text": "15.\n다음 파이썬 코드의 알맞는 출력값을 작성하시오.",
      "question_html": "<p data-ke-size=\"size16\" style=\"color: #555555; text-align: start;\"><b>15.<span><span><span> 다음 파이썬 코드의 알맞는 출력값을 작성하시오.</span></span></span></b></p>",
      "options": "",
      "images": [],
      "code": "a = {'한국', '중국', '일본'}\na.add('베트남')\na.add('중국')\na.remove('일본')\na.update({'홍콩', '한국', '태국'})\nprint(a)",
      "code_html": "<div class=\"code-line\">a <span style=\"color: #a71d5d;\">=</span> {<span style=\"color: #63a35c;\">'한국'</span>, <span style=\"color: #63a35c;\">'중국'</span>, <span style=\"color: #63a35c;\">'일본'</span>}</div>\n<div class=\"code-line\">a.add(<span style=\"color: #63a35c;\">'베트남'</span>)</div>\n<div class=\"code-line\">a.add(<span style=\"color: #63a35c;\">'중국'</span>)</div>\n<div class=\"code-line\">a.remove(<span style=\"color: #63a35c;\">'일본'</span>)</div>\n<div class=\"code-line\">a.update({<span style=\"color: #63a35c;\">'홍콩'</span>, <span style=\"color: #63a35c;\">'한국'</span>, <span style=\"color: #63a35c;\">'태국'</span>})</div>\n<div class=\"code-line\"><span style=\"color: #066de2;\">print</span>(a)</div>",
      "answer": "{'한국', '중국', '베트남', '홍콩', '태국'}",
      "answer_html": "<p data-ke-size=\"size16\" style=\"color: #555555; text-align: start;\">{'한국', '중국', '베트남', '홍콩', '태국'}</p>"
    },
    {
      "number": 16,
      "text": "16.\n다음 성적 테이블에서 과목별 점수의 평균이 90점 이상인 '과목이름', '최소점수', '최대점수' 를 검색하고자 한다. [조건]을 참고하여 적합한 SQL문을 작성하시오.\n조건\n: - where사용하지 말하야 한다. - SELECT절에 별칭을 사용하여 작성해야 한다. - SQL 구문 마지막에 세미콜론 생락 가능하다. - 반드시 GROUP BY와 having을 사용해야 한다. - 집계함수를 사용해야 한다.",
      "question_html": "<p data-ke-size=\"size16\" style=\"color: #555555; text-align: start;\"><b>16.<span><span><span>다음 성적 테이블에서 과목별 점수의 평균이 90점 이상인 '과목이름', '최소점수', '최대점수' 를 검색하고자 한다. [조건]을 참고하여 적합한 SQL문을 작성하시오.</span></span></span></b></p>\n<p data-ke-size=\"size16\" style=\"color: #555555; text-align: start;\"><b>조건</b>:  - where사용하지 말하야 한다. - SELECT절에 별칭을 사용하여 작성해야 한다. - SQL 구문 마지막에 세미콜론 생락 가능하다. - 반드시 GROUP BY와 having을 사용해야 한다. - 집계함수를 사용해야 한다.</p>",
      "options": "",
      "images": [],
      "code": null,
      "code_html": null,
      "answer": "SELECT 과목이름 ,MIN(점수) AS 최소점수 ,MAX(점수) AS 최대점수 From 성적 GROUP BY 과목이름 HAVING AVG(점수) >= 90",
      "answer_html": "<p data-ke-size=\"size16\" style=\"color: #555555; text-align: start;\">SELECT   과목이름   ,MIN(점수) AS 최소점수   ,MAX(점수) AS 최대점수 From    성적 GROUP BY    과목이름 HAVING   AVG(점수) &gt;= 90</p>"
    },
    {
      "number": 17,
      "text": "17.\n다음 JAVA 코드에서 알맞는 출력 값을 작성하시오.",
      "question_html": "<p data-ke-size=\"size16\" style=\"color: #555555; text-align: start;\"><b>17.<span><span><span><span>다음 JAVA 코드에서 알맞는 출력 값을 작성하시오.</span></span></span></span></b></p>",
      "options": "",
      "images": [],
      "code": "abstact class Vehicle {\n    String name;\n    abstract public String getName(String val);\n    public String getName() {\n            return \"Vehicle name: \" + name;\n    }\n}\nclass Car extends Vehicle {\n    public Car(String val) {\n            name=super.name=val;\n    }\n    public String getName(String val) {\n            return \"Car name:\" + val;\n    }\n    public String getName(byte val[]) {\n            return \"Car name:\" + val;\n    }\n}\npublic class Main {\n    public static void main(String[] args) {\n    Vehicle obj = new Car(\"Spark\");\n    System.out.println(obj.getName());\n    }\n}",
      "code_html": "<div class=\"code-line\">abstact <span style=\"color: #a71d5d;\">class</span> Vehicle {</div>\n<div class=\"code-line\">    <span style=\"color: #066de2;\">String</span> name;</div>\n<div class=\"code-line\">    <span style=\"color: #a71d5d;\">abstract</span> <span style=\"color: #a71d5d;\">public</span> <span style=\"color: #066de2;\">String</span> getName(<span style=\"color: #066de2;\">String</span> val);</div>\n<div class=\"code-line\">    <span style=\"color: #a71d5d;\">public</span> <span style=\"color: #066de2;\">String</span> getName() {</div>\n<div class=\"code-line\">            <span style=\"color: #a71d5d;\">return</span> <span style=\"color: #63a35c;\">\"Vehicle name: \"</span> <span style=\"color: #a71d5d;\">+</span> name;</div>\n<div class=\"code-line\">    }</div>\n<div class=\"code-line\">}</div>\n<div class=\"code-line\"><span style=\"color: #a71d5d;\">class</span> Car <span style=\"color: #a71d5d;\">extends</span> Vehicle {</div>\n<div class=\"code-line\">    <span style=\"color: #a71d5d;\">public</span> Car(<span style=\"color: #066de2;\">String</span> val) {</div>\n<div class=\"code-line\">            name<span style=\"color: #a71d5d;\">=</span><span style=\"color: #a71d5d;\">super</span>.name<span style=\"color: #a71d5d;\">=</span>val;</div>\n<div class=\"code-line\">    }</div>\n<div class=\"code-line\">    <span style=\"color: #a71d5d;\">public</span> <span style=\"color: #066de2;\">String</span> getName(<span style=\"color: #066de2;\">String</span> val) {</div>\n<div class=\"code-line\">            <span style=\"color: #a71d5d;\">return</span> <span style=\"color: #63a35c;\">\"Car name:\"</span> <span style=\"color: #a71d5d;\">+</span> val;</div>\n<div class=\"code-line\">    }</div>\n<div class=\"code-line\">    <span style=\"color: #a71d5d;\">public</span> <span style=\"color: #066de2;\">String</span> getName(<span style=\"color: #066de2;\">byte</span> val[]) {</div>\n<div class=\"code-line\">            <span style=\"color: #a71d5d;\">return</span> <span style=\"color: #63a35c;\">\"Car name:\"</span> <span style=\"color: #a71d5d;\">+</span> val;</div>\n<div class=\"code-line\">    }</div>\n<div class=\"code-line\">}</div>\n<div class=\"code-line\"><span style=\"color: #a71d5d;\">public</span> <span style=\"color: #a71d5d;\">class</span> Main {</div>\n<div class=\"code-line\">    <span style=\"color: #a71d5d;\">public</span> <span style=\"color: #a71d5d;\">static</span> <span style=\"color: #a71d5d;\">void</span> main(<span style=\"color: #066de2;\">String</span>[] args) {</div>\n<div class=\"code-line\">    Vehicle obj <span style=\"color: #a71d5d;\">=</span> <span style=\"color: #a71d5d;\">new</span> Car(<span style=\"color: #63a35c;\">\"Spark\"</span>);</div>\n<div class=\"code-line\">    <span style=\"color: #066de2;\">System</span>.<span style=\"color: #066de2;\">out</span>.<span style=\"color: #066de2;\">println</span>(obj.getName());</div>\n<div class=\"code-line\">    }</div>\n<div class=\"code-line\">}</div>",
      "answer": "Vehicle name: Spark",
      "answer_html": "<p data-ke-size=\"size16\" style=\"color: #555555; text-align: start;\">Vehicle name: Spark</p>"
    },
    {
      "number": 18,
      "text": "18.\n다음은 스키마와 관련된 내용이다. 각 괄호안에 알맞는 답을 작성하시오.\n(보기가 있습니다.)\n구분\n내용\n( 1 ) 스키마\n- 사용자나 응용 프로그래머가 개인의 입장에서 필요한 데이터베이스의 논리적 구조를 정의한다. - 전체 데이터베이스의 한 논리적인 부분으로 볼 수 있기 때문에 서브 스키마라고도 한다. - 하나의 데이터베이스 시스템에는 여러 개의 외부 스키마가 존재할 수 있다. - 하나의 외부 스키마를 여러개의 응용 프로그램 혹은 사용자가 공유할 수 있다.\n( 2 )\n스키마\n- 데이터베이스의 전체적인 논리적 구조로, 모든 응용 프로그램이나 사용자들이 필요로 하는 데이터를 종합한 조직 전체의 데이터베이스로 하나만 존재한다. - 개체 간의 관계(Relationship)와 제약 조건을 나타내고 데이터베이스의 접근 권한, 보안 및 무결성 규칙에 관한 명세를 정의한다. - 데이터베이스 파일에 저장되는 데이터의 형태를 나타내는 것이다. - 기관이나 조직체의 관점에서 데이터베이스를 정의한 것이다\n( 3 )\n스키마\n- 물리적인 저장장치 입장에서 데이터가 저장되는 방법을 기술한 것이다. - 실제 데이터베이스에 저장될 레코드의 물리적인 구조를 정의한다. - 저장 데이터 항목의 표현방법, 내부 레코드의 물리적 순서, 인덱스 유/무 등을 나타낸다. - 시스템 프로그래머나 시스템 설계자가 관리한다.",
      "question_html": "<p data-ke-size=\"size16\" style=\"color: #555555; text-align: start;\"><b>18.<span><span><span><span><b><span>다음은 스키마와 관련된 내용이다. 각 괄호안에 알맞는 답을 작성하시오.</span></b></span></span></span></span></b></p>\n<p data-ke-size=\"size16\" style=\"color: #555555; text-align: start;\"><u>(보기가 있습니다.)</u></p>\n<table border=\"1\" data-ke-align=\"alignLeft\" style=\"border-collapse: collapse; width: 100%;\">\n<tbody>\n<tr>\n<td style=\"width: 19.4186%; text-align: center;\">구분</td>\n<td style=\"width: 80.5814%; text-align: center;\">내용</td>\n</tr>\n<tr>\n<td style=\"width: 19.4186%; text-align: center;\">(   1   ) 스키마</td>\n<td style=\"width: 80.5814%; text-align: left;\">- 사용자나 응용 프로그래머가 개인의 입장에서 필요한 데이터베이스의 논리적 구조를 정의한다. - 전체 데이터베이스의 한 논리적인 부분으로 볼 수 있기 때문에 서브 스키마라고도 한다. - 하나의 데이터베이스 시스템에는 여러 개의 외부 스키마가 존재할 수 있다. - 하나의 외부 스키마를 여러개의 응용 프로그램 혹은 사용자가 공유할 수 있다.</td>\n</tr>\n<tr>\n<td style=\"width: 19.4186%; text-align: center;\">(   2   )<span style=\"color: #333333; text-align: center;\">스키마</span></td>\n<td style=\"width: 80.5814%; text-align: left;\">- 데이터베이스의 전체적인 논리적 구조로, 모든 응용 프로그램이나 사용자들이 필요로 하는 데이터를 종합한 조직 전체의 데이터베이스로 하나만 존재한다. - 개체 간의 관계(Relationship)와 제약 조건을 나타내고 데이터베이스의 접근 권한, 보안 및 무결성 규칙에 관한 명세를 정의한다. - 데이터베이스 파일에 저장되는 데이터의 형태를 나타내는 것이다. - 기관이나 조직체의 관점에서 데이터베이스를 정의한 것이다</td>\n</tr>\n<tr>\n<td style=\"width: 19.4186%; text-align: center;\">(   3   )<span style=\"color: #333333; text-align: center;\">스키마</span></td>\n<td style=\"width: 80.5814%; text-align: left;\">- 물리적인 저장장치 입장에서 데이터가 저장되는 방법을 기술한 것이다. - 실제 데이터베이스에 저장될 레코드의 물리적인 구조를 정의한다.  - 저장 데이터 항목의 표현방법, 내부 레코드의 물리적 순서, 인덱스 유/무 등을 나타낸다. - 시스템 프로그래머나 시스템 설계자가 관리한다.</td>\n</tr>\n</tbody>\n</table>",
      "options": "",
      "images": [],
      "code": null,
      "code_html": null,
      "answer": "1. 외부\n2. 개념\n3. 내부",
      "answer_html": "<p data-ke-size=\"size16\" style=\"color: #555555; text-align: start;\">1. 외부</p>\n<p data-ke-size=\"size16\" style=\"color: #555555; text-align: start;\">2. 개념</p>\n<p data-ke-size=\"size16\" style=\"color: #555555; text-align: start;\">3. 내부</p>"
    },
    {
      "number": 19,
      "text": "19.\n다음 아래 제어 흐름 그래프가 분기 커버리지를 만족하기 위한 테스팅 순서를 쓰시오.",
      "question_html": "<p data-ke-size=\"size16\" style=\"color: #555555; text-align: start;\"><b>19.<span><span><span><span><span> <b>다음 아래 제어 흐름 그래프가 분기 커버리지를 만족하기 위한 테스팅 순서를 쓰시오.</b></span></span></span></span></span></b></p>",
      "options": "",
      "images": [],
      "code": null,
      "code_html": null,
      "answer": "1234561, 124567 or 1234567, 124561",
      "answer_html": "<p data-ke-size=\"size16\" style=\"color: #555555; text-align: start;\">1234561, 124567  or 1234567, 124561</p>"
    },
    {
      "number": 20,
      "text": "20.\n다음 자바 코드에 대한 출력 값을 작성하시오.",
      "question_html": "<p data-ke-size=\"size16\" style=\"color: #555555; text-align: start;\"><b>20.<span><span><span><span>다음 자바 코드에 대한 출력 값을 작성하시오.</span></span></span></span></b></p>",
      "options": "",
      "images": [],
      "code": "class Parent {\n    int x = 100;\n    Parent() {\n        this(500);\n    }\n    Parent(int x) {\n        this.x = x;\n    }\n    int getX() {\n        return x;\n    }\n}\nclass Child extends Parent {\n    int x = 4000;\n    Child() {\n        this(5000);\n    }\n    Child(int x) {\n        this.x = x;\n    }\n}\npublic class Main {\n    public static void main(String[] args) {\n        Child obj = new Child();\n        System.out.println(obj.getX());\n    }\n}",
      "code_html": "<div class=\"code-line\"><span style=\"color: #a71d5d;\">class</span> Parent {</div>\n<div class=\"code-line\">    <span style=\"color: #066de2;\">int</span> x <span style=\"color: #a71d5d;\">=</span> <span style=\"color: #0099cc;\">100</span>;</div>\n<div class=\"code-line\">    Parent() {</div>\n<div class=\"code-line\">        <span style=\"color: #a71d5d;\">this</span>(<span style=\"color: #0099cc;\">500</span>);</div>\n<div class=\"code-line\">    }</div>\n<div class=\"code-line\">    Parent(<span style=\"color: #066de2;\">int</span> x) {</div>\n<div class=\"code-line\">        <span style=\"color: #a71d5d;\">this</span>.x <span style=\"color: #a71d5d;\">=</span> x;</div>\n<div class=\"code-line\">    }</div>\n<div class=\"code-line\">    <span style=\"color: #066de2;\">int</span> getX() {</div>\n<div class=\"code-line\">        <span style=\"color: #a71d5d;\">return</span> x;</div>\n<div class=\"code-line\">    }</div>\n<div class=\"code-line\">}</div>\n<div class=\"code-line\"><span style=\"color: #a71d5d;\">class</span> Child <span style=\"color: #a71d5d;\">extends</span> Parent {</div>\n<div class=\"code-line\">    <span style=\"color: #066de2;\">int</span> x <span style=\"color: #a71d5d;\">=</span> <span style=\"color: #0099cc;\">4000</span>;</div>\n<div class=\"code-line\">    Child() {</div>\n<div class=\"code-line\">        <span style=\"color: #a71d5d;\">this</span>(<span style=\"color: #0099cc;\">5000</span>);</div>\n<div class=\"code-line\">    }</div>\n<div class=\"code-line\">    Child(<span style=\"color: #066de2;\">int</span> x) {</div>\n<div class=\"code-line\">        <span style=\"color: #a71d5d;\">this</span>.x <span style=\"color: #a71d5d;\">=</span> x;</div>\n<div class=\"code-line\">    }</div>\n<div class=\"code-line\">}</div>\n<div class=\"code-line\"><span style=\"color: #a71d5d;\">public</span> <span style=\"color: #a71d5d;\">class</span> Main {</div>\n<div class=\"code-line\">    <span style=\"color: #a71d5d;\">public</span> <span style=\"color: #a71d5d;\">static</span> <span style=\"color: #a71d5d;\">void</span> main(<span style=\"color: #066de2;\">String</span>[] args) {</div>\n<div class=\"code-line\">        Child obj <span style=\"color: #a71d5d;\">=</span> <span style=\"color: #a71d5d;\">new</span> Child();</div>\n<div class=\"code-line\">        <span style=\"color: #066de2;\">System</span>.<span style=\"color: #066de2;\">out</span>.<span style=\"color: #066de2;\">println</span>(obj.getX());</div>\n<div class=\"code-line\">    }</div>\n<div class=\"code-line\">}</div>",
      "answer": "500",
      "answer_html": "<p data-ke-size=\"size16\">500</p>"
    }
  ]
}